pyDE1/__init__.py
pyDE1/btcontrack.py
pyDE1/config.py
pyDE1/config_load.py
pyDE1/controller.py
pyDE1/exceptions.py
pyDE1/flow_sequencer.py
pyDE1/flow_sequencer_impl.py
pyDE1/lock_logger.py
pyDE1/pyde1_logging.py
pyDE1/run.py
pyDE1/scanner.py
pyDE1/send_single_message.py
pyDE1/shutdown_manager.py
pyDE1/singleton.py
pyDE1/source_data.py
pyDE1/status_reporter.py
pyDE1/supervise.py
pyDE1/task_logger.py
pyDE1/utils.py
pyDE1/utils_public.py
pyDE1/version_check_3_8.py
pyDE1/api/__init__.py
pyDE1/api/inbound/__init__.py
pyDE1/api/inbound/http/__init__.py
pyDE1/api/inbound/http/run.py
pyDE1/api/outbound/__init__.py
pyDE1/api/outbound/mqtt/__init__.py
pyDE1/api/outbound/mqtt/run.py
pyDE1/bledev/__init__.py
pyDE1/bledev/managed_bleak_client.py
pyDE1/bledev/managed_bleak_device.py
pyDE1/database/__init__.py
pyDE1/database/create_history_record.py
pyDE1/database/insert.py
pyDE1/database/manage.py
pyDE1/database/recorder_control.py
pyDE1/database/run.py
pyDE1/database/write_notifications.py
pyDE1/database/schema/schema.001.sql
pyDE1/database/schema/schema.002.sql
pyDE1/database/schema/schema.003.sql
pyDE1/database/schema/upgrade.001.002.sql
pyDE1/database/schema/upgrade.002.003.sql
pyDE1/de1/__init__.py
pyDE1/de1/ble.py
pyDE1/de1/c_api.py
pyDE1/de1/de1.py
pyDE1/de1/events.py
pyDE1/de1/firmware_file.py
pyDE1/de1/handlers.py
pyDE1/de1/notifications.py
pyDE1/de1/profile.py
pyDE1/dispatcher/__init__.py
pyDE1/dispatcher/dispatcher.py
pyDE1/dispatcher/implementation.py
pyDE1/dispatcher/mapping.py
pyDE1/dispatcher/payloads.py
pyDE1/dispatcher/resource.py
pyDE1/dispatcher/validate.py
pyDE1/event_manager/__init__.py
pyDE1/event_manager/event_manager.py
pyDE1/event_manager/events.py
pyDE1/event_manager/payloads.py
pyDE1/scale/__init__.py
pyDE1/scale/acaia.py
pyDE1/scale/atomax_skale_ii.py
pyDE1/scale/estimator.py
pyDE1/scale/events.py
pyDE1/scale/felicita_arc.py
pyDE1/scale/generic_scale.py
pyDE1/scale/processor.py
pyDE1/services/config/pyde1-replay.conf
pyDE1-2.0.0.dist-info/LICENSE
pyDE1-2.0.0.dist-info/METADATA
pyDE1-2.0.0.dist-info/WHEEL
pyDE1-2.0.0.dist-info/entry_points.txt
pyDE1-2.0.0.dist-info/top_level.txt
pyDE1-2.0.0.dist-info/RECORD
