Metadata-Version: 2.1
Name: pyDE1
Version: 2.0.0
Summary: Controller for Decent Espresso DE1
Home-page: https://pyde1.readthedocs.io/en/stable/
Author: Jeff Kletsky
Author-email: git-commits@allycomm.com
Project-URL: Bug Tracker, https://github.com/jeffsf/pyDE1/issues
Classifier: Development Status :: 5 - Production/Stable
Classifier: Programming Language :: Python :: 3
Classifier: Programming Language :: Python :: 3.9
Classifier: Programming Language :: Python :: 3.10
Classifier: Programming Language :: Python :: 3.11
Classifier: Framework :: AsyncIO
Classifier: Intended Audience :: Developers
Classifier: Topic :: Home Automation
Classifier: License :: OSI Approved :: GNU General Public License v3 (GPLv3)
Requires-Python: >=3.9
License-File: LICENSE
Requires-Dist: aiosqlite (>=0.18.0)
Requires-Dist: bleak (>=0.19.5)
Requires-Dist: paho-mqtt (>=1.6.1)
Requires-Dist: pyparsing (>=3.0.9)
Requires-Dist: PyYAML (>=6.0)
Requires-Dist: requests (>=2.28.2)
